arekore/__init__.py
arekore/data1d.py
arekore/data2d.py
arekore/dummy.py
arekore/viz.py
arekore-0.2.0.dist-info/LICENSE
arekore-0.2.0.dist-info/WHEEL
arekore-0.2.0.dist-info/METADATA
arekore-0.2.0.dist-info/RECORD
