Metadata-Version: 2.1
Name: arekore
Version: 0.2.0
Summary: 記述統計のためのクラスや可視化のあれこれ。ダミーデータも作れるよ。
Home-page: https://github.com/mohira
Author: mohira
Requires-Python: >=3.8,<3.12
Classifier: Programming Language :: Python :: 3
Classifier: Programming Language :: Python :: 3.10
Classifier: Programming Language :: Python :: 3.8
Classifier: Programming Language :: Python :: 3.9
Requires-Dist: japanize-matplotlib (>=1.1.3,<2.0.0)
Requires-Dist: matplotlib (>=3.5.0,<4.0.0)
Requires-Dist: numpy (>=1.23.1,<2.0.0)
Requires-Dist: pandas (>=1.4.3,<2.0.0)
Requires-Dist: scikit-learn (>=1.1.2,<2.0.0)
Requires-Dist: scipy (>=1.9.0,<2.0.0)
Requires-Dist: statsmodels (>=0.13.2,<0.14.0)
Requires-Dist: tabulate (>=0.8.10,<0.9.0)
Project-URL: Repository, https://github.com/mohira/arekore
